setup.py
nezha/__init__.py
nezha/celery_helper.py
nezha/container.py
nezha/env.py
nezha/errors.py
nezha/file.py
nezha/fun.py
nezha/func.py
nezha/hash.py
nezha/idcard.py
nezha/imports.py
nezha/obj.py
nezha/package.py
nezha/phone.py
nezha/picture.py
nezha/pyjwt.py
nezha/redis.py
nezha/sql.py
nezha/uargparse.py
nezha/udict.py
nezha/uexcel.py
nezha/ufabric.py
nezha/ujson.py
nezha/umongo.py
nezha/upandas.py
nezha/url.py
nezha/usetup.py
nezha/ustring.py
nezha/utime.py
nezha.egg-info/PKG-INFO
nezha.egg-info/SOURCES.txt
nezha.egg-info/dependency_links.txt
nezha.egg-info/top_level.txt
nezha/aliyun/__init__.py
nezha/aliyun/oss.py
nezha/aliyun/robot.py
nezha/aliyun/uemail.py
nezha/aliyun/docker/__init__.py
nezha/aliyun/log_service/__init__.py
nezha/aliyun/log_service/clean_log.py
nezha/encryption/__init__.py
nezha/encryption/aes.py
nezha/encryption/des.py
nezha/encryption/rsa2.py