Metadata-Version: 1.0
Name: nezha
Version: 0.0.66
Summary: nezha, pysuway's utils
Home-page: UNKNOWN
Author: UNKNOWN
Author-email: UNKNOWN
License: UNKNOWN
Platform: UNKNOWN
